aegis/__init__.py
aegis/aegis_.py
aegis/build.py
aegis/config.py
aegis/database.py
aegis/hydra.py
aegis/mailer.py
aegis/model.py
aegis/stdlib.py
aegis/threadpool.py
aegis/webapp.py
aegis/sql/auditing-mysql.sql
aegis/sql/auditing-pgsql.sql
aegis/sql/build-mysql.sql
aegis/sql/build-pgsql.sql
aegis/sql/cache_system.sql
aegis/sql/email_system-pgsql.sql
aegis/sql/google_signin.sql
aegis/sql/hydra-mysql.sql
aegis/sql/hydra-pgsql.sql
aegis/sql/member_auth.sql
aegis/sql/monitor-mysql.sql
aegis/sql/reports.sql
aegis/sql/usage-pgsql.sql
aegis/templates/build.html
aegis/templates/build_confirm.html
aegis/templates/build_form.html
aegis/templates/build_view.html
aegis/templates/error_message.txt
aegis/templates/frame.html
aegis/templates/hydra.html
aegis/templates/hydra_form.html
aegis/templates/hydra_queue.html
aegis/templates/index.html
aegis/templates/report.html
aegis/templates/report_form.html
aegis/templates/reports.html
aegis/templates/usage.html
aegis/templates/w3.css
aegis_tools-3.0.1.dist-info/licenses/LICENSE
aegis_tools-3.0.1.dist-info/METADATA
aegis_tools-3.0.1.dist-info/WHEEL
aegis_tools-3.0.1.dist-info/entry_points.txt
aegis_tools-3.0.1.dist-info/top_level.txt
aegis_tools-3.0.1.dist-info/RECORD
