Metadata-Version: 2.4
Name: aegis-tools
Version: 3.0.1
Summary: Aegis is a set of battle-tested tools and tricks to help everyone make better software
Home-page: https://github.com/mdagosta/aegis
Author: Michael D'Agosta
Author-email: mdagosta@codebug.com
Classifier: Programming Language :: Python :: 3
Classifier: Operating System :: OS Independent
Requires-Python: >=3.6
License-File: LICENSE
Requires-Dist: bcrypt==3.2.0
Requires-Dist: pympler
Requires-Dist: pyreferrer
Requires-Dist: python-dateutil
Requires-Dist: requests
Requires-Dist: tornado>=6.2.0
Requires-Dist: twine>=6.1.0
Requires-Dist: user_agents
Dynamic: author
Dynamic: author-email
Dynamic: classifier
Dynamic: home-page
Dynamic: license-file
Dynamic: requires-dist
Dynamic: requires-python
Dynamic: summary
